rlrunner/__init__.py
rlrunner/runner.py
rlrunner/agents/__init__.py
rlrunner/agents/base_agent.py
rlrunner/agents/simple_agent.py
rlrunner/envs/__init__.py
rlrunner/envs/base_env.py
rlrunner/envs/gym_wrapper_env.py
rlrunner/envs/simple_env.py
rlrunner/stats/__init__.py
rlrunner/stats/base_stat_saver.py
rlrunner/stats/simple_ss.py
rlrunner/termination/__init__.py
rlrunner/termination/base_termination_condition.py
rlrunner/termination/dynamic_tc.py
rlrunner/termination/simple_tc.py
rlrunner-1.0.2.dist-info/DESCRIPTION.rst
rlrunner-1.0.2.dist-info/METADATA
rlrunner-1.0.2.dist-info/RECORD
rlrunner-1.0.2.dist-info/WHEEL
rlrunner-1.0.2.dist-info/metadata.json
rlrunner-1.0.2.dist-info/top_level.txt
