Metadata-Version: 2.0
Name: rlrunner
Version: 1.0.2
Summary: A framework for Reinforcement Learning experimentation and run simulation
Home-page: https://github.com/PriestTheBeast/RLRunner
Author: Miguel Martins
Author-email: mfmartins1996@gmail.com
License: UNKNOWN
Platform: UNKNOWN
Classifier: Programming Language :: Python :: 3
Classifier: License :: OSI Approved :: MIT License
Requires-Python: >=3.6
Requires-Dist: numpy
Requires-Dist: gym
Requires-Dist: matplotlib
